lambda_genai_builder/__init__.py
lambda_genai_builder/cli.py
lambda_genai_builder/code_content.py
lambda_genai_builder-0.0.3.dist-info/LICENSE.txt
lambda_genai_builder-0.0.3.dist-info/METADATA
lambda_genai_builder-0.0.3.dist-info/WHEEL
lambda_genai_builder-0.0.3.dist-info/entry_points.txt
lambda_genai_builder-0.0.3.dist-info/top_level.txt
lambda_genai_builder-0.0.3.dist-info/RECORD
